changelog_generator/__init__.py
changelog_generator/calls.py
changelog_generator/entry_point.py
changelog_generator/generator.py
changelog_generator/log_handlers.py
src/__init__.py
src/gitlab_changelog_generator/__init__.py
src/gitlab_changelog_generator/calls.py
src/gitlab_changelog_generator/generator.py
src/gitlab_changelog_generator/log_handlers.py
gitlab_changelog_generator-1.0.7.dist-info/LICENSE.md
gitlab_changelog_generator-1.0.7.dist-info/METADATA
gitlab_changelog_generator-1.0.7.dist-info/WHEEL
gitlab_changelog_generator-1.0.7.dist-info/entry_points.txt
gitlab_changelog_generator-1.0.7.dist-info/top_level.txt
gitlab_changelog_generator-1.0.7.dist-info/RECORD
