Metadata-Version: 2.1
Name: gitlab-changelog-generator
Version: 1.0.7
Summary: A small command line utility for generating CHANGELOG.md files from GitLab repository commits
Home-page: https://github.com/stuartmccoll/gitlab-changelog-generator
Author: Stuart McColl
Author-email: it@stuartmccoll.co.uk
License: UNKNOWN
Keywords: gitlab changelog python
Platform: UNKNOWN
Classifier: Environment :: Console
Classifier: Programming Language :: Python
Classifier: Programming Language :: Python :: 3.6
Classifier: Programming Language :: Python :: 3.7
Classifier: Programming Language :: Python :: 3 :: Only
Classifier: Topic :: Software Development :: Libraries :: Python Modules
Classifier: License :: OSI Approved :: MIT License
Classifier: Operating System :: OS Independent
Requires-Dist: requests
Requires-Dist: python-dateutil
